accudata/__init__.py
accudata-1.0.1.dist-info/LICENSE
accudata-1.0.1.dist-info/METADATA
accudata-1.0.1.dist-info/WHEEL
accudata-1.0.1.dist-info/top_level.txt
accudata-1.0.1.dist-info/RECORD
