Metadata-Version: 2.1
Name: accudata
Version: 1.0.1
Summary: Simple module to store data with arbitrary structure in dict or Pandas DataFrame
Home-page: https://github.com/vongostev/accudata
Author: Pavel Gostev
Author-email: gostev.pavel@physics.msu.ru
License: UNKNOWN
Platform: UNKNOWN
Classifier: Programming Language :: Python :: 3
Classifier: License :: OSI Approved :: MIT License
Classifier: Operating System :: OS Independent
Requires-Python: >=3.6
License-File: LICENSE
Requires-Dist: numpy
Requires-Dist: pandas
